Metadata-Version: 2.3
Name: swarmauri_tool_jupytervalidatenotebook
Version: 0.7.5
Summary: A tool that validates a NotebookNode object against the Jupyter Notebook schema using nbformat, ensuring structural correctness.
License: Apache-2.0
Author: Jacob Stewart
Author-email: jacob@swarmauri.com
Requires-Python: >=3.10,<3.13
Classifier: License :: OSI Approved :: Apache Software License
Classifier: Programming Language :: Python :: 3.10
Classifier: Programming Language :: Python :: 3.11
Classifier: Programming Language :: Python :: 3.12
Classifier: Programming Language :: Python :: 3.13
Requires-Dist: nbformat (>=5.10.4)
Requires-Dist: pydantic (>=2.10.6)
Requires-Dist: swarmauri_base
Requires-Dist: swarmauri_core
Requires-Dist: swarmauri_standard
Requires-Dist: typing_extensions (>=4.12.2)
